meraki_syslog_server/README_mac.md
meraki_syslog_server/__init__.py
meraki_syslog_server/main.py
meraki_syslog_server/meraki_mx_syslog_parser.py
meraki_syslog_server/randomize_mac.py
meraki_syslog_server/requirements.txt
meraki_syslog_server/samples/meraki_events_mac_rand.log
meraki_syslog_server/samples/meraki_firewall_mac_rand.log
meraki_syslog_server/samples/meraki_urls_mac_rand.log
meraki_syslog_server-0.1.0.dist-info/LICENSE
meraki_syslog_server-0.1.0.dist-info/METADATA
meraki_syslog_server-0.1.0.dist-info/WHEEL
meraki_syslog_server-0.1.0.dist-info/RECORD
