Metadata-Version: 2.1
Name: meraki-syslog-server
Version: 0.1.0
Summary: Meraki MX Syslog Parser
Author: reinaldopenno
Author-email: rapenno@gmail.com
Requires-Python: >=3.11,<4.0
Classifier: Programming Language :: Python :: 3
Classifier: Programming Language :: Python :: 3.11
